README.rst
setup.py
django_modelduplication.egg-info/PKG-INFO
django_modelduplication.egg-info/SOURCES.txt
django_modelduplication.egg-info/dependency_links.txt
django_modelduplication.egg-info/top_level.txt
modelduplication/__init__.py
modelduplication/admin.py
modelduplication/tests/__init__.py